dotenv.py
django_dotenv-1.4.1.dist-info/DESCRIPTION.rst
django_dotenv-1.4.1.dist-info/METADATA
django_dotenv-1.4.1.dist-info/metadata.json
django_dotenv-1.4.1.dist-info/RECORD
django_dotenv-1.4.1.dist-info/top_level.txt
django_dotenv-1.4.1.dist-info/WHEEL
